{
  "season": 2026,
  "asOf": "2026년 7월 8일 기준",
  "fetchedAt": "2026-07-08T21:45:17.329Z",
  "source": {
    "standings": "https://eng.koreabaseball.com/Standings/TeamStandings.aspx",
    "hitter": "https://m.koreabaseball.com/Kbo/Record/TeamRecord_hitter.aspx",
    "pitcher": "https://m.koreabaseball.com/Kbo/Record/TeamRecord_pitcher.aspx"
  },
  "teams": [
    {
      "id": "lg",
      "rank": 1,
      "games": 84,
      "wins": 52,
      "losses": 32,
      "draws": 0,
      "winPct": "0.619",
      "battingAverage": "0.272",
      "homeRuns": 75,
      "runs": 430,
      "hits": 762,
      "era": "4.47",
      "runsAllowed": 393,
      "strikeouts": 560
    },
    {
      "id": "samsung",
      "rank": 2,
      "games": 84,
      "wins": 50,
      "losses": 32,
      "draws": 2,
      "winPct": "0.610",
      "battingAverage": "0.275",
      "homeRuns": 74,
      "runs": 479,
      "hits": 796,
      "era": "4.10",
      "runsAllowed": 373,
      "strikeouts": 608
    },
    {
      "id": "kt",
      "rank": 3,
      "games": 83,
      "wins": 47,
      "losses": 35,
      "draws": 1,
      "winPct": "0.573",
      "battingAverage": "0.282",
      "homeRuns": 56,
      "runs": 454,
      "hits": 810,
      "era": "4.72",
      "runsAllowed": 419,
      "strikeouts": 629
    },
    {
      "id": "kia",
      "rank": 4,
      "games": 85,
      "wins": 44,
      "losses": 39,
      "draws": 2,
      "winPct": "0.530",
      "battingAverage": "0.269",
      "homeRuns": 98,
      "runs": 445,
      "hits": 784,
      "era": "4.30",
      "runsAllowed": 400,
      "strikeouts": 608
    },
    {
      "id": "doosan",
      "rank": 5,
      "games": 86,
      "wins": 43,
      "losses": 41,
      "draws": 2,
      "winPct": "0.512",
      "battingAverage": "0.269",
      "homeRuns": 63,
      "runs": 395,
      "hits": 791,
      "era": "3.94",
      "runsAllowed": 380,
      "strikeouts": 707
    },
    {
      "id": "hanwha",
      "rank": 6,
      "games": 81,
      "wins": 39,
      "losses": 40,
      "draws": 2,
      "winPct": "0.494",
      "battingAverage": "0.273",
      "homeRuns": 95,
      "runs": 475,
      "hits": 779,
      "era": "4.50",
      "runsAllowed": 410,
      "strikeouts": 586
    },
    {
      "id": "nc",
      "rank": 7,
      "games": 81,
      "wins": 39,
      "losses": 41,
      "draws": 1,
      "winPct": "0.488",
      "battingAverage": "0.278",
      "homeRuns": 79,
      "runs": 426,
      "hits": 766,
      "era": "4.57",
      "runsAllowed": 411,
      "strikeouts": 651
    },
    {
      "id": "lotte",
      "rank": 8,
      "games": 84,
      "wins": 38,
      "losses": 44,
      "draws": 2,
      "winPct": "0.463",
      "battingAverage": "0.261",
      "homeRuns": 64,
      "runs": 373,
      "hits": 762,
      "era": "4.40",
      "runsAllowed": 413,
      "strikeouts": 679
    },
    {
      "id": "ssg",
      "rank": 9,
      "games": 85,
      "wins": 31,
      "losses": 51,
      "draws": 3,
      "winPct": "0.378",
      "battingAverage": "0.261",
      "homeRuns": 94,
      "runs": 423,
      "hits": 764,
      "era": "5.86",
      "runsAllowed": 533,
      "strikeouts": 636
    },
    {
      "id": "kiwoom",
      "rank": 10,
      "games": 87,
      "wins": 29,
      "losses": 57,
      "draws": 1,
      "winPct": "0.337",
      "battingAverage": "0.234",
      "homeRuns": 51,
      "runs": 295,
      "hits": 682,
      "era": "5.04",
      "runsAllowed": 463,
      "strikeouts": 657
    }
  ]
}
